{
  "song": {
    "id": "west-2007-97",
    "title": "Last Fire",
    "artist": {
      "id": "a-linkin-park",
      "name": "Linkin Park"
    },
    "genre": "western"
  },
  "rankingYear": 2007,
  "rank": 97,
  "cdInfo": [
    {
      "title": "Last Fire",
      "type": "single",
      "releaseDate": "2007-05-13"
    },
    {
      "title": "Storm Diaries",
      "type": "album",
      "releaseDate": "2007-06-01"
    }
  ],
  "externalLinks": {
    "amazonMusic": "https://music.amazon.co.jp/albums/example1",
    "amazonCD": "https://amazon.co.jp/dp/example1",
    "appleMusic": "https://music.apple.com/jp/album/example1"
  },
  "artistSongs": [
    {
      "rank": 21,
      "song": {
        "id": "west-2009-21",
        "title": "Dancing Summer",
        "artist": {
          "id": "a-linkin-park",
          "name": "Linkin Park"
        },
        "genre": "western"
      },
      "year": 2009
    },
    {
      "rank": 46,
      "song": {
        "id": "west-2009-46",
        "title": "Running Storm",
        "artist": {
          "id": "a-linkin-park",
          "name": "Linkin Park"
        },
        "genre": "western"
      },
      "year": 2009
    },
    {
      "rank": 55,
      "song": {
        "id": "west-2009-55",
        "title": "Rose Love",
        "artist": {
          "id": "a-linkin-park",
          "name": "Linkin Park"
        },
        "genre": "western"
      },
      "year": 2009
    },
    {
      "rank": 70,
      "song": {
        "id": "west-2009-70",
        "title": "Electric River",
        "artist": {
          "id": "a-linkin-park",
          "name": "Linkin Park"
        },
        "genre": "western"
      },
      "year": 2009
    },
    {
      "rank": 81,
      "song": {
        "id": "west-2009-81",
        "title": "Wave Forever",
        "artist": {
          "id": "a-linkin-park",
          "name": "Linkin Park"
        },
        "genre": "western"
      },
      "year": 2009
    },
    {
      "rank": 85,
      "song": {
        "id": "west-2009-85",
        "title": "Diamond Rain",
        "artist": {
          "id": "a-linkin-park",
          "name": "Linkin Park"
        },
        "genre": "western"
      },
      "year": 2009
    },
    {
      "rank": 88,
      "song": {
        "id": "west-2009-88",
        "title": "Sun Rain",
        "artist": {
          "id": "a-linkin-park",
          "name": "Linkin Park"
        },
        "genre": "western"
      },
      "year": 2009
    },
    {
      "rank": 96,
      "song": {
        "id": "west-2009-96",
        "title": "Midnight Thunder",
        "artist": {
          "id": "a-linkin-park",
          "name": "Linkin Park"
        },
        "genre": "western"
      },
      "year": 2009
    },
    {
      "rank": 99,
      "song": {
        "id": "west-2009-99",
        "title": "Midnight Fire",
        "artist": {
          "id": "a-linkin-park",
          "name": "Linkin Park"
        },
        "genre": "western"
      },
      "year": 2009
    },
    {
      "rank": 15,
      "song": {
        "id": "west-2008-15",
        "title": "Running Rain",
        "artist": {
          "id": "a-linkin-park",
          "name": "Linkin Park"
        },
        "genre": "western"
      },
      "year": 2008
    },
    {
      "rank": 21,
      "song": {
        "id": "west-2008-21",
        "title": "Bridge Love",
        "artist": {
          "id": "a-linkin-park",
          "name": "Linkin Park"
        },
        "genre": "western"
      },
      "year": 2008
    },
    {
      "rank": 29,
      "song": {
        "id": "west-2008-29",
        "title": "Into the Bridge",
        "artist": {
          "id": "a-linkin-park",
          "name": "Linkin Park"
        },
        "genre": "western"
      },
      "year": 2008
    },
    {
      "rank": 53,
      "song": {
        "id": "west-2008-53",
        "title": "Running Bridge",
        "artist": {
          "id": "a-linkin-park",
          "name": "Linkin Park"
        },
        "genre": "western"
      },
      "year": 2008
    },
    {
      "rank": 62,
      "song": {
        "id": "west-2008-62",
        "title": "Electric City",
        "artist": {
          "id": "a-linkin-park",
          "name": "Linkin Park"
        },
        "genre": "western"
      },
      "year": 2008
    },
    {
      "rank": 83,
      "song": {
        "id": "west-2008-83",
        "title": "Star Lights",
        "artist": {
          "id": "a-linkin-park",
          "name": "Linkin Park"
        },
        "genre": "western"
      },
      "year": 2008
    },
    {
      "rank": 12,
      "song": {
        "id": "west-2007-12",
        "title": "Mountain Lights",
        "artist": {
          "id": "a-linkin-park",
          "name": "Linkin Park"
        },
        "genre": "western"
      },
      "year": 2007
    },
    {
      "rank": 23,
      "song": {
        "id": "west-2007-23",
        "title": "Star Forever",
        "artist": {
          "id": "a-linkin-park",
          "name": "Linkin Park"
        },
        "genre": "western"
      },
      "year": 2007
    },
    {
      "rank": 78,
      "song": {
        "id": "west-2007-78",
        "title": "Chasing Wave",
        "artist": {
          "id": "a-linkin-park",
          "name": "Linkin Park"
        },
        "genre": "western"
      },
      "year": 2007
    },
    {
      "rank": 93,
      "song": {
        "id": "west-2007-93",
        "title": "Falling Diamond",
        "artist": {
          "id": "a-linkin-park",
          "name": "Linkin Park"
        },
        "genre": "western"
      },
      "year": 2007
    },
    {
      "rank": 28,
      "song": {
        "id": "west-2006-28",
        "title": "Wild Sky",
        "artist": {
          "id": "a-linkin-park",
          "name": "Linkin Park"
        },
        "genre": "western"
      },
      "year": 2006
    },
    {
      "rank": 31,
      "song": {
        "id": "west-2006-31",
        "title": "Last Diamond",
        "artist": {
          "id": "a-linkin-park",
          "name": "Linkin Park"
        },
        "genre": "western"
      },
      "year": 2006
    },
    {
      "rank": 33,
      "song": {
        "id": "west-2006-33",
        "title": "Wild Flame",
        "artist": {
          "id": "a-linkin-park",
          "name": "Linkin Park"
        },
        "genre": "western"
      },
      "year": 2006
    },
    {
      "rank": 63,
      "song": {
        "id": "west-2006-63",
        "title": "Never Fire",
        "artist": {
          "id": "a-linkin-park",
          "name": "Linkin Park"
        },
        "genre": "western"
      },
      "year": 2006
    },
    {
      "rank": 24,
      "song": {
        "id": "west-2005-24",
        "title": "Fire Tears",
        "artist": {
          "id": "a-linkin-park",
          "name": "Linkin Park"
        },
        "genre": "western"
      },
      "year": 2005
    },
    {
      "rank": 33,
      "song": {
        "id": "west-2005-33",
        "title": "Shining Summer",
        "artist": {
          "id": "a-linkin-park",
          "name": "Linkin Park"
        },
        "genre": "western"
      },
      "year": 2005
    },
    {
      "rank": 41,
      "song": {
        "id": "west-2005-41",
        "title": "Dusk Fire",
        "artist": {
          "id": "a-linkin-park",
          "name": "Linkin Park"
        },
        "genre": "western"
      },
      "year": 2005
    },
    {
      "rank": 42,
      "song": {
        "id": "west-2005-42",
        "title": "Golden Sun",
        "artist": {
          "id": "a-linkin-park",
          "name": "Linkin Park"
        },
        "genre": "western"
      },
      "year": 2005
    },
    {
      "rank": 52,
      "song": {
        "id": "west-2005-52",
        "title": "Broken Storm",
        "artist": {
          "id": "a-linkin-park",
          "name": "Linkin Park"
        },
        "genre": "western"
      },
      "year": 2005
    },
    {
      "rank": 69,
      "song": {
        "id": "west-2005-69",
        "title": "Sky Lights",
        "artist": {
          "id": "a-linkin-park",
          "name": "Linkin Park"
        },
        "genre": "western"
      },
      "year": 2005
    },
    {
      "rank": 79,
      "song": {
        "id": "west-2005-79",
        "title": "Golden Thunder",
        "artist": {
          "id": "a-linkin-park",
          "name": "Linkin Park"
        },
        "genre": "western"
      },
      "year": 2005
    },
    {
      "rank": 91,
      "song": {
        "id": "west-2005-91",
        "title": "Ocean Moonlight",
        "artist": {
          "id": "a-linkin-park",
          "name": "Linkin Park"
        },
        "genre": "western"
      },
      "year": 2005
    },
    {
      "rank": 12,
      "song": {
        "id": "west-2004-12",
        "title": "Dusk Soul",
        "artist": {
          "id": "a-linkin-park",
          "name": "Linkin Park"
        },
        "genre": "western"
      },
      "year": 2004
    },
    {
      "rank": 15,
      "song": {
        "id": "west-2004-15",
        "title": "Wind Rain",
        "artist": {
          "id": "a-linkin-park",
          "name": "Linkin Park"
        },
        "genre": "western"
      },
      "year": 2004
    },
    {
      "rank": 27,
      "song": {
        "id": "west-2004-27",
        "title": "Dusk Moonlight",
        "artist": {
          "id": "a-linkin-park",
          "name": "Linkin Park"
        },
        "genre": "western"
      },
      "year": 2004
    },
    {
      "rank": 44,
      "song": {
        "id": "west-2004-44",
        "title": "Golden Dawn",
        "artist": {
          "id": "a-linkin-park",
          "name": "Linkin Park"
        },
        "genre": "western"
      },
      "year": 2004
    },
    {
      "rank": 64,
      "song": {
        "id": "west-2004-64",
        "title": "Dancing Dusk",
        "artist": {
          "id": "a-linkin-park",
          "name": "Linkin Park"
        },
        "genre": "western"
      },
      "year": 2004
    },
    {
      "rank": 92,
      "song": {
        "id": "west-2004-92",
        "title": "Under the Mountain",
        "artist": {
          "id": "a-linkin-park",
          "name": "Linkin Park"
        },
        "genre": "western"
      },
      "year": 2004
    },
    {
      "rank": 40,
      "song": {
        "id": "west-2003-40",
        "title": "Under the Wind",
        "artist": {
          "id": "a-linkin-park",
          "name": "Linkin Park"
        },
        "genre": "western"
      },
      "year": 2003
    },
    {
      "rank": 62,
      "song": {
        "id": "west-2003-62",
        "title": "Sun Sky",
        "artist": {
          "id": "a-linkin-park",
          "name": "Linkin Park"
        },
        "genre": "western"
      },
      "year": 2003
    },
    {
      "rank": 70,
      "song": {
        "id": "west-2003-70",
        "title": "Wild Silver",
        "artist": {
          "id": "a-linkin-park",
          "name": "Linkin Park"
        },
        "genre": "western"
      },
      "year": 2003
    },
    {
      "rank": 4,
      "song": {
        "id": "west-2002-04",
        "title": "In the End",
        "artist": {
          "id": "a-linkin-park",
          "name": "Linkin Park"
        },
        "genre": "western"
      },
      "year": 2002
    },
    {
      "rank": 57,
      "song": {
        "id": "west-2002-57",
        "title": "Shadow Dreams",
        "artist": {
          "id": "a-linkin-park",
          "name": "Linkin Park"
        },
        "genre": "western"
      },
      "year": 2002
    },
    {
      "rank": 100,
      "song": {
        "id": "west-2002-100",
        "title": "Dancing Rain",
        "artist": {
          "id": "a-linkin-park",
          "name": "Linkin Park"
        },
        "genre": "western"
      },
      "year": 2002
    },
    {
      "rank": 27,
      "song": {
        "id": "west-2001-27",
        "title": "Wave Sky",
        "artist": {
          "id": "a-linkin-park",
          "name": "Linkin Park"
        },
        "genre": "western"
      },
      "year": 2001
    },
    {
      "rank": 30,
      "song": {
        "id": "west-2001-30",
        "title": "Broken Ice",
        "artist": {
          "id": "a-linkin-park",
          "name": "Linkin Park"
        },
        "genre": "western"
      },
      "year": 2001
    },
    {
      "rank": 46,
      "song": {
        "id": "west-2001-46",
        "title": "Running Dawn",
        "artist": {
          "id": "a-linkin-park",
          "name": "Linkin Park"
        },
        "genre": "western"
      },
      "year": 2001
    },
    {
      "rank": 58,
      "song": {
        "id": "west-2001-58",
        "title": "Dancing Summer",
        "artist": {
          "id": "a-linkin-park",
          "name": "Linkin Park"
        },
        "genre": "western"
      },
      "year": 2001
    },
    {
      "rank": 73,
      "song": {
        "id": "west-2001-73",
        "title": "Last Bridge",
        "artist": {
          "id": "a-linkin-park",
          "name": "Linkin Park"
        },
        "genre": "western"
      },
      "year": 2001
    },
    {
      "rank": 78,
      "song": {
        "id": "west-2001-78",
        "title": "Rose Forever",
        "artist": {
          "id": "a-linkin-park",
          "name": "Linkin Park"
        },
        "genre": "western"
      },
      "year": 2001
    },
    {
      "rank": 80,
      "song": {
        "id": "west-2001-80",
        "title": "Under the Diamond",
        "artist": {
          "id": "a-linkin-park",
          "name": "Linkin Park"
        },
        "genre": "western"
      },
      "year": 2001
    },
    {
      "rank": 82,
      "song": {
        "id": "west-2001-82",
        "title": "River Way",
        "artist": {
          "id": "a-linkin-park",
          "name": "Linkin Park"
        },
        "genre": "western"
      },
      "year": 2001
    },
    {
      "rank": 94,
      "song": {
        "id": "west-2001-94",
        "title": "Into the Dusk",
        "artist": {
          "id": "a-linkin-park",
          "name": "Linkin Park"
        },
        "genre": "western"
      },
      "year": 2001
    },
    {
      "rank": 24,
      "song": {
        "id": "west-2000-24",
        "title": "Wave Soul",
        "artist": {
          "id": "a-linkin-park",
          "name": "Linkin Park"
        },
        "genre": "western"
      },
      "year": 2000
    },
    {
      "rank": 52,
      "song": {
        "id": "west-2000-52",
        "title": "Shining Gold",
        "artist": {
          "id": "a-linkin-park",
          "name": "Linkin Park"
        },
        "genre": "western"
      },
      "year": 2000
    },
    {
      "rank": 78,
      "song": {
        "id": "west-2000-78",
        "title": "Midnight Moon",
        "artist": {
          "id": "a-linkin-park",
          "name": "Linkin Park"
        },
        "genre": "western"
      },
      "year": 2000
    },
    {
      "rank": 82,
      "song": {
        "id": "west-2000-82",
        "title": "River Tears",
        "artist": {
          "id": "a-linkin-park",
          "name": "Linkin Park"
        },
        "genre": "western"
      },
      "year": 2000
    },
    {
      "rank": 92,
      "song": {
        "id": "west-2000-92",
        "title": "Star Soul",
        "artist": {
          "id": "a-linkin-park",
          "name": "Linkin Park"
        },
        "genre": "western"
      },
      "year": 2000
    },
    {
      "rank": 98,
      "song": {
        "id": "west-2000-98",
        "title": "Crystal Love",
        "artist": {
          "id": "a-linkin-park",
          "name": "Linkin Park"
        },
        "genre": "western"
      },
      "year": 2000
    }
  ]
}
