{
  "song": {
    "id": "west-2009-01",
    "title": "Boom Boom Pow",
    "artist": {
      "id": "a-black-eyed-peas",
      "name": "Black Eyed Peas"
    },
    "genre": "western"
  },
  "rankingYear": 2009,
  "rank": 1,
  "cdInfo": [
    {
      "title": "Boom Boom Pow",
      "type": "single",
      "releaseDate": "2009-01-01"
    },
    {
      "title": "Best of Snow",
      "type": "album",
      "releaseDate": "2009-08-10"
    }
  ],
  "externalLinks": {
    "amazonMusic": "https://music.amazon.co.jp/albums/example1",
    "amazonCD": "https://amazon.co.jp/dp/example1",
    "appleMusic": "https://music.apple.com/jp/album/example1"
  },
  "artistSongs": [
    {
      "rank": 4,
      "song": {
        "id": "west-2009-04",
        "title": "I Gotta Feeling",
        "artist": {
          "id": "a-black-eyed-peas",
          "name": "Black Eyed Peas"
        },
        "genre": "western"
      },
      "year": 2009
    },
    {
      "rank": 3,
      "song": {
        "id": "west-2003-03",
        "title": "Where Is the Love?",
        "artist": {
          "id": "a-black-eyed-peas",
          "name": "Black Eyed Peas"
        },
        "genre": "western"
      },
      "year": 2003
    }
  ]
}
