{
  "song": {
    "id": "west-2023-54",
    "title": "Lost in Flame",
    "artist": {
      "id": "a-miley",
      "name": "Miley Cyrus"
    },
    "genre": "western"
  },
  "rankingYear": 2023,
  "rank": 54,
  "cdInfo": [
    {
      "title": "Lost in Flame",
      "type": "single",
      "releaseDate": "2023-09-06"
    },
    {
      "title": "The Sky Album",
      "type": "album",
      "releaseDate": "2023-05-22"
    }
  ],
  "externalLinks": {
    "amazon": "https://amazon.co.jp/dp/example1",
    "appleMusic": "https://music.apple.com/jp/album/example1"
  },
  "artistSongs": [
    {
      "rank": 19,
      "song": {
        "id": "west-2025-19",
        "title": "Road Moonlight",
        "artist": {
          "id": "a-miley",
          "name": "Miley Cyrus"
        },
        "genre": "western"
      },
      "year": 2025
    },
    {
      "rank": 22,
      "song": {
        "id": "west-2025-22",
        "title": "Under the Thunder",
        "artist": {
          "id": "a-miley",
          "name": "Miley Cyrus"
        },
        "genre": "western"
      },
      "year": 2025
    },
    {
      "rank": 38,
      "song": {
        "id": "west-2025-38",
        "title": "Broken Wave",
        "artist": {
          "id": "a-miley",
          "name": "Miley Cyrus"
        },
        "genre": "western"
      },
      "year": 2025
    },
    {
      "rank": 74,
      "song": {
        "id": "west-2025-74",
        "title": "River Moonlight",
        "artist": {
          "id": "a-miley",
          "name": "Miley Cyrus"
        },
        "genre": "western"
      },
      "year": 2025
    },
    {
      "rank": 77,
      "song": {
        "id": "west-2025-77",
        "title": "Chasing Sky",
        "artist": {
          "id": "a-miley",
          "name": "Miley Cyrus"
        },
        "genre": "western"
      },
      "year": 2025
    },
    {
      "rank": 20,
      "song": {
        "id": "west-2023-20",
        "title": "Dancing Rain",
        "artist": {
          "id": "a-miley",
          "name": "Miley Cyrus"
        },
        "genre": "western"
      },
      "year": 2023
    },
    {
      "rank": 21,
      "song": {
        "id": "west-2023-21",
        "title": "Road Heart",
        "artist": {
          "id": "a-miley",
          "name": "Miley Cyrus"
        },
        "genre": "western"
      },
      "year": 2023
    },
    {
      "rank": 34,
      "song": {
        "id": "west-2023-34",
        "title": "Sky Sky",
        "artist": {
          "id": "a-miley",
          "name": "Miley Cyrus"
        },
        "genre": "western"
      },
      "year": 2023
    },
    {
      "rank": 35,
      "song": {
        "id": "west-2023-35",
        "title": "Into the Star",
        "artist": {
          "id": "a-miley",
          "name": "Miley Cyrus"
        },
        "genre": "western"
      },
      "year": 2023
    },
    {
      "rank": 49,
      "song": {
        "id": "west-2023-49",
        "title": "Midnight Bridge",
        "artist": {
          "id": "a-miley",
          "name": "Miley Cyrus"
        },
        "genre": "western"
      },
      "year": 2023
    },
    {
      "rank": 73,
      "song": {
        "id": "west-2023-73",
        "title": "Lost in Rain",
        "artist": {
          "id": "a-miley",
          "name": "Miley Cyrus"
        },
        "genre": "western"
      },
      "year": 2023
    },
    {
      "rank": 76,
      "song": {
        "id": "west-2023-76",
        "title": "Falling Dusk",
        "artist": {
          "id": "a-miley",
          "name": "Miley Cyrus"
        },
        "genre": "western"
      },
      "year": 2023
    },
    {
      "rank": 91,
      "song": {
        "id": "west-2023-91",
        "title": "Fading Thunder",
        "artist": {
          "id": "a-miley",
          "name": "Miley Cyrus"
        },
        "genre": "western"
      },
      "year": 2023
    },
    {
      "rank": 83,
      "song": {
        "id": "west-2022-83",
        "title": "Midnight Sky",
        "artist": {
          "id": "a-miley",
          "name": "Miley Cyrus"
        },
        "genre": "western"
      },
      "year": 2022
    },
    {
      "rank": 89,
      "song": {
        "id": "west-2022-89",
        "title": "Ocean Dreams",
        "artist": {
          "id": "a-miley",
          "name": "Miley Cyrus"
        },
        "genre": "western"
      },
      "year": 2022
    },
    {
      "rank": 94,
      "song": {
        "id": "west-2022-94",
        "title": "Silver Soul",
        "artist": {
          "id": "a-miley",
          "name": "Miley Cyrus"
        },
        "genre": "western"
      },
      "year": 2022
    },
    {
      "rank": 32,
      "song": {
        "id": "west-2021-32",
        "title": "Wind Forever",
        "artist": {
          "id": "a-miley",
          "name": "Miley Cyrus"
        },
        "genre": "western"
      },
      "year": 2021
    },
    {
      "rank": 47,
      "song": {
        "id": "west-2021-47",
        "title": "City Moonlight",
        "artist": {
          "id": "a-miley",
          "name": "Miley Cyrus"
        },
        "genre": "western"
      },
      "year": 2021
    },
    {
      "rank": 64,
      "song": {
        "id": "west-2021-64",
        "title": "Under the Sun",
        "artist": {
          "id": "a-miley",
          "name": "Miley Cyrus"
        },
        "genre": "western"
      },
      "year": 2021
    },
    {
      "rank": 71,
      "song": {
        "id": "west-2021-71",
        "title": "Fading Road",
        "artist": {
          "id": "a-miley",
          "name": "Miley Cyrus"
        },
        "genre": "western"
      },
      "year": 2021
    },
    {
      "rank": 12,
      "song": {
        "id": "west-2020-12",
        "title": "Sweet River",
        "artist": {
          "id": "a-miley",
          "name": "Miley Cyrus"
        },
        "genre": "western"
      },
      "year": 2020
    },
    {
      "rank": 20,
      "song": {
        "id": "west-2020-20",
        "title": "Summer Heart",
        "artist": {
          "id": "a-miley",
          "name": "Miley Cyrus"
        },
        "genre": "western"
      },
      "year": 2020
    },
    {
      "rank": 22,
      "song": {
        "id": "west-2020-22",
        "title": "Into the Dusk",
        "artist": {
          "id": "a-miley",
          "name": "Miley Cyrus"
        },
        "genre": "western"
      },
      "year": 2020
    },
    {
      "rank": 67,
      "song": {
        "id": "west-2020-67",
        "title": "Running Wave",
        "artist": {
          "id": "a-miley",
          "name": "Miley Cyrus"
        },
        "genre": "western"
      },
      "year": 2020
    },
    {
      "rank": 73,
      "song": {
        "id": "west-2020-73",
        "title": "Storm Moonlight",
        "artist": {
          "id": "a-miley",
          "name": "Miley Cyrus"
        },
        "genre": "western"
      },
      "year": 2020
    },
    {
      "rank": 91,
      "song": {
        "id": "west-2020-91",
        "title": "Diamond Heart",
        "artist": {
          "id": "a-miley",
          "name": "Miley Cyrus"
        },
        "genre": "western"
      },
      "year": 2020
    }
  ]
}
